Metadata-Version: 1.1
Name: scisweeper
Version: 0.0.2.post0.dev51
Summary: scisweeper - scientific parameter sweeper
Home-page: https://github.com/scisweeper/scisweeper
Author: Jan Janssen
Author-email: janssen@mpie.de
License: BSD
Keywords: scisweeper
Platform: UNKNOWN
Classifier: Development Status :: 5 - Production/Stable
Classifier: Topic :: Scientific/Engineering :: Physics
Classifier: License :: OSI Approved :: BSD License
Classifier: Intended Audience :: Science/Research
Classifier: Operating System :: OS Independent
Classifier: Programming Language :: Python :: 2.7
Classifier: Programming Language :: Python :: 3
Classifier: Programming Language :: Python :: 3.4
Classifier: Programming Language :: Python :: 3.5
Classifier: Programming Language :: Python :: 3.6
Classifier: Programming Language :: Python :: 3.7
